<?xml version="1.0" encoding="UTF-8"?>
<clinical_study rank="78">
  <!-- This xml conforms to an XML Schema at:
    https://clinicaltrials.gov/ct2/html/images/info/public.xsd
 and an XML DTD at:
    https://clinicaltrials.gov/ct2/html/images/info/public.dtd -->
  <required_header>
    <download_date>ClinicalTrials.gov processed this data on December 13, 2015</download_date>
    <link_text>Link to the current ClinicalTrials.gov record.</link_text>
    <url>https://clinicaltrials.gov/show/NCT01519960</url>
  </required_header>
  <id_info>
    <org_study_id>YV25718</org_study_id>
    <secondary_id>2011-002732-70</secondary_id>
    <nct_id>NCT01519960</nct_id>
  </id_info>
  <brief_title>A Study of Pegasys (Peginterferon Alfa-2a) Versus Untreated Control in Children With HBeAg Positive Chronic Hepatitis B</brief_title>
  <official_title>A Phase IIIb Parallel Group, Open Label Study of Pegylated Interferon Alfa-2a Monotherapy (PEG-IFN, Ro 25-8310) Compared to Untreated Control in Children With HBeAg Positive Chronic Hepatitis B</official_title>
  <sponsors>
    <lead_sponsor>
      <agency>Hoffmann-La Roche</agency>
      <agency_class>Industry</agency_class>
    </lead_sponsor>
  </sponsors>
  <source>Hoffmann-La Roche</source>
  <oversight_info>
    <authority>United States: Food and Drug Administration</authority>
  </oversight_info>
  <brief_summary>
    <textblock>
      This parallel group, open label study will evaluate the safety and efficacy of Pegasys
      (peginterferon alfa-2a) versus untreated control in children (age 3 years to &lt;18 years at
      baseline) with HBeAg positive chronic hepatitis B. Children without advanced fibrosis and
      without cirrhosis will be randomized 2:1 to treatment Group A, receiving Pegasys 45-180 mcg
      subcutaneously weekly for 48 weeks, or to the untreated control Group B. Children with
      advanced fibrosis will be assigned to treatment group C and receive 48 weeks of treatment
      with Pegasys. Children in the untreated control Group B who have not experienced
      seroconversion 48 weeks after randomization may enter the Switch Arm to receive 48 weeks of
      Pegasys treatment. This offer will be available for 1 year following 48 weeks from
      randomization. Anticipated time on study treatment is 48 weeks. All subjects will be
      followed up for 5 years after the end of treatment (A,C,Switch)/principal observation (B)
      period.
    </textblock>
  </brief_summary>
  <overall_status>Active, not recruiting</overall_status>
  <start_date>July 2012</start_date>
  <completion_date type="Anticipated">August 2022</completion_date>
  <primary_completion_date type="Anticipated">August 2022</primary_completion_date>
  <phase>Phase 3</phase>
  <study_type>Interventional</study_type>
  <study_design>Allocation: Non-Randomized, Endpoint Classification: Safety/Efficacy Study, Intervention Model: Parallel Assignment, Masking: Open Label, Primary Purpose: Treatment</study_design>
  <primary_outcome>
    <measure>HBeAg seroconversion (loss of HBeAg and presence of anti-HBe) 24 weeks after end of treatment/principal observation period with a further 4.5 years of follow-up</measure>
    <time_frame>24 weeks post-treatment/principal observation period</time_frame>
    <safety_issue>No</safety_issue>
  </primary_outcome>
  <secondary_outcome>
    <measure>HBsAg seroconversion (loss of HBsAg and presence of anti-HBs)</measure>
    <time_frame>up to 8 years</time_frame>
    <safety_issue>No</safety_issue>
  </secondary_outcome>
  <secondary_outcome>
    <measure>Loss of HBeAg/HBsAg</measure>
    <time_frame>up to 8 years</time_frame>
    <safety_issue>No</safety_issue>
  </secondary_outcome>
  <secondary_outcome>
    <measure>Serum alanine aminotransferase (ALT) levels</measure>
    <time_frame>up to 8 years</time_frame>
    <safety_issue>No</safety_issue>
  </secondary_outcome>
  <secondary_outcome>
    <measure>Proportion of normal ALT</measure>
    <time_frame>up to 8 years</time_frame>
    <safety_issue>No</safety_issue>
  </secondary_outcome>
  <secondary_outcome>
    <measure>HBV DNA levels</measure>
    <time_frame>up to 8 years</time_frame>
    <safety_issue>No</safety_issue>
  </secondary_outcome>
  <secondary_outcome>
    <measure>Change in liver elasticity (elastography)</measure>
    <time_frame>from baseline to Week 72</time_frame>
    <safety_issue>No</safety_issue>
  </secondary_outcome>
  <secondary_outcome>
    <measure>Group C: Change in histological findings (liver biopsy)</measure>
    <time_frame>from baseline to Week 72</time_frame>
    <safety_issue>No</safety_issue>
  </secondary_outcome>
  <secondary_outcome>
    <measure>Pharmacokinetics: Area under the concentration-time curve (AUC)</measure>
    <time_frame>Weeks 1 and 24, pre-dose and 24-48, 72-96 and 168 hours post-dose</time_frame>
    <safety_issue>No</safety_issue>
  </secondary_outcome>
  <secondary_outcome>
    <measure>Safety: Incidence of adverse events</measure>
    <time_frame>up to 8 years</time_frame>
    <safety_issue>No</safety_issue>
  </secondary_outcome>
  <secondary_outcome>
    <measure>Safety: Growth</measure>
    <time_frame>up to 8 years</time_frame>
    <safety_issue>No</safety_issue>
  </secondary_outcome>
  <number_of_arms>4</number_of_arms>
  <enrollment type="Actual">165</enrollment>
  <condition>Hepatitis B, Chronic</condition>
  <arm_group>
    <arm_group_label>A Pegasys</arm_group_label>
    <arm_group_type>Experimental</arm_group_type>
  </arm_group>
  <arm_group>
    <arm_group_label>B Untreated Control</arm_group_label>
    <arm_group_type>No Intervention</arm_group_type>
  </arm_group>
  <arm_group>
    <arm_group_label>C Fibrosis non-randomized</arm_group_label>
    <arm_group_type>Experimental</arm_group_type>
  </arm_group>
  <arm_group>
    <arm_group_label>Switch</arm_group_label>
    <arm_group_type>Experimental</arm_group_type>
  </arm_group>
  <intervention>
    <intervention_type>Drug</intervention_type>
    <intervention_name>peginterferon alfa-2a [Pegasys]</intervention_name>
    <description>Body surface area adapted doses of 45-180 mcg subcutaneously weekly for 48 weeks, Weeks 1- 48</description>
    <arm_group_label>A Pegasys</arm_group_label>
    <arm_group_label>C Fibrosis non-randomized</arm_group_label>
  </intervention>
  <intervention>
    <intervention_type>Drug</intervention_type>
    <intervention_name>peginterferon alfa-2a [Pegasys]</intervention_name>
    <description>Body surface area adapted doses of 45-180 mcg subcutaneously weekly for 48 weeks, after Week 48 for Group B patients who have not experienced HBeAg seroconversion</description>
    <arm_group_label>Switch</arm_group_label>
  </intervention>
  <eligibility>
    <criteria>
      <textblock>
        Inclusion Criteria:

          -  Male or female patients, 3 years to &lt;18 years of age at baseline

          -  Positive HBsAg for more than 6 months

          -  Positive HBeAg and detectable HBV DNA at screening

          -  Negative anti-HBs and anti-HBe at screening

          -  A liver biopsy obtained within the past 2 years prior to baseline (and more than 6
             months after the end of previous therapy for hepatitis B) to confirm the presence of
             advanced fibrosis or exclude cirrhosis

          -  Compensated liver disease (Child-Pugh Class A)

          -  Elevated serum alanine transferase (ALT)

          -  Normal thyroid gland function at screening

        Exclusion Criteria:

          -  Subjects with cirrhosis

          -  Subjects must not have received investigational drugs or licensed treatments with
             anti-HBV activity within 6 months of baseline. Subjects who are expected to need
             systemic antiviral therapy other than that provided by the study at any time during
             their participation in the study are also excluded

          -  Known hypersensitivity to peginterferon

          -  Positive test results at screening for hepatitis A, hepatitis C, hepatitis D or HIV
             infection

          -  History or evidence of medical condition associated with chronic liver disease other
             than chronic hepatitis B

          -  History or evidence of bleeding from esophageal varices

          -  Decompensated liver disease (e.g. ascites, Child-Pugh Class B or C)

          -  History of immunologically mediated disease

          -  Pregnant or lactating females
      </textblock>
    </criteria>
    <gender>Both</gender>
    <minimum_age>3 Years</minimum_age>
    <maximum_age>17 Years</maximum_age>
    <healthy_volunteers>No</healthy_volunteers>
  </eligibility>
  <overall_official>
    <last_name>Clinical Trials</last_name>
    <role>Study Director</role>
    <affiliation>Hoffmann-La Roche</affiliation>
  </overall_official>
  <location>
    <facility>
      <address>
        <city>San Francisco</city>
        <state>California</state>
        <zip>94143</zip>
        <country>United States</country>
      </address>
    </facility>
  </location>
  <location>
    <facility>
      <address>
        <city>Baltimore</city>
        <state>Maryland</state>
        <zip>21287-5554</zip>
        <country>United States</country>
      </address>
    </facility>
  </location>
  <location>
    <facility>
      <address>
        <city>Boston</city>
        <state>Massachusetts</state>
        <zip>02115</zip>
        <country>United States</country>
      </address>
    </facility>
  </location>
  <location>
    <facility>
      <address>
        <city>St. Louis</city>
        <state>Missouri</state>
        <zip>63104</zip>
        <country>United States</country>
      </address>
    </facility>
  </location>
  <location>
    <facility>
      <address>
        <city>Houston</city>
        <state>Texas</state>
        <zip>77030</zip>
        <country>United States</country>
      </address>
    </facility>
  </location>
  <location>
    <facility>
      <address>
        <city>Seattle</city>
        <state>Washington</state>
        <zip>98105</zip>
        <country>United States</country>
      </address>
    </facility>
  </location>
  <location>
    <facility>
      <address>
        <city>Sydney</city>
        <state>New South Wales</state>
        <zip>2145</zip>
        <country>Australia</country>
      </address>
    </facility>
  </location>
  <location>
    <facility>
      <address>
        <city>North Adelaide</city>
        <state>South Australia</state>
        <zip>5006</zip>
        <country>Australia</country>
      </address>
    </facility>
  </location>
  <location>
    <facility>
      <address>
        <city>Melbourne</city>
        <state>Victoria</state>
        <zip>3053</zip>
        <country>Australia</country>
      </address>
    </facility>
  </location>
  <location>
    <facility>
      <address>
        <city>Bruxelles</city>
        <zip>1200</zip>
        <country>Belgium</country>
      </address>
    </facility>
  </location>
  <location>
    <facility>
      <address>
        <city>Gent</city>
        <zip>9000</zip>
        <country>Belgium</country>
      </address>
    </facility>
  </location>
  <location>
    <facility>
      <address>
        <city>Sofia</city>
        <zip>1612</zip>
        <country>Bulgaria</country>
      </address>
    </facility>
  </location>
  <location>
    <facility>
      <address>
        <city>Varna</city>
        <zip>9000</zip>
        <country>Bulgaria</country>
      </address>
    </facility>
  </location>
  <location>
    <facility>
      <address>
        <city>Beijing</city>
        <zip>100039</zip>
        <country>China</country>
      </address>
    </facility>
  </location>
  <location>
    <facility>
      <address>
        <city>Beijing</city>
        <zip>100069</zip>
        <country>China</country>
      </address>
    </facility>
  </location>
  <location>
    <facility>
      <address>
        <city>Changchun</city>
        <zip>130021</zip>
        <country>China</country>
      </address>
    </facility>
  </location>
  <location>
    <facility>
      <address>
        <city>Chongqing</city>
        <zip>400038</zip>
        <country>China</country>
      </address>
    </facility>
  </location>
  <location>
    <facility>
      <address>
        <city>Guangzhou</city>
        <zip>510060</zip>
        <country>China</country>
      </address>
    </facility>
  </location>
  <location>
    <facility>
      <address>
        <city>Guangzhou</city>
        <zip>510630</zip>
        <country>China</country>
      </address>
    </facility>
  </location>
  <location>
    <facility>
      <address>
        <city>Kunming</city>
        <zip>650032</zip>
        <country>China</country>
      </address>
    </facility>
  </location>
  <location>
    <facility>
      <address>
        <city>Shanghai</city>
        <zip>200235</zip>
        <country>China</country>
      </address>
    </facility>
  </location>
  <location>
    <facility>
      <address>
        <city>Urumqi</city>
        <zip>830000</zip>
        <country>China</country>
      </address>
    </facility>
  </location>
  <location>
    <facility>
      <address>
        <city>Wuhan</city>
        <zip>430030</zip>
        <country>China</country>
      </address>
    </facility>
  </location>
  <location>
    <facility>
      <address>
        <city>Xi'an</city>
        <zip>710061</zip>
        <country>China</country>
      </address>
    </facility>
  </location>
  <location>
    <facility>
      <address>
        <city>Wuppertal</city>
        <zip>42283</zip>
        <country>Germany</country>
      </address>
    </facility>
  </location>
  <location>
    <facility>
      <address>
        <city>Haifa</city>
        <zip>31096</zip>
        <country>Israel</country>
      </address>
    </facility>
  </location>
  <location>
    <facility>
      <address>
        <city>Jerusalem</city>
        <zip>9112001</zip>
        <country>Israel</country>
      </address>
    </facility>
  </location>
  <location>
    <facility>
      <address>
        <city>Nahariya</city>
        <zip>22100</zip>
        <country>Israel</country>
      </address>
    </facility>
  </location>
  <location>
    <facility>
      <address>
        <city>Bologna</city>
        <state>Emilia-Romagna</state>
        <zip>40138</zip>
        <country>Italy</country>
      </address>
    </facility>
  </location>
  <location>
    <facility>
      <address>
        <city>Torino</city>
        <state>Piemonte</state>
        <zip>10126</zip>
        <country>Italy</country>
      </address>
    </facility>
  </location>
  <location>
    <facility>
      <address>
        <city>Bydgoszcz</city>
        <zip>85-030</zip>
        <country>Poland</country>
      </address>
    </facility>
  </location>
  <location>
    <facility>
      <address>
        <city>Krakow</city>
        <zip>31-202</zip>
        <country>Poland</country>
      </address>
    </facility>
  </location>
  <location>
    <facility>
      <address>
        <city>Poznan</city>
        <zip>60-693</zip>
        <country>Poland</country>
      </address>
    </facility>
  </location>
  <location>
    <facility>
      <address>
        <city>Łodz</city>
        <zip>91-347</zip>
        <country>Poland</country>
      </address>
    </facility>
  </location>
  <location>
    <facility>
      <address>
        <city>Arkhangelsk</city>
        <zip>163045</zip>
        <country>Russian Federation</country>
      </address>
    </facility>
  </location>
  <location>
    <facility>
      <address>
        <city>Moscow</city>
        <zip>115446</zip>
        <country>Russian Federation</country>
      </address>
    </facility>
  </location>
  <location>
    <facility>
      <address>
        <city>Moscow</city>
        <zip>119991</zip>
        <country>Russian Federation</country>
      </address>
    </facility>
  </location>
  <location>
    <facility>
      <address>
        <city>Saint Petersburg</city>
        <zip>197022</zip>
        <country>Russian Federation</country>
      </address>
    </facility>
  </location>
  <location>
    <facility>
      <address>
        <city>Samara</city>
        <zip>443100</zip>
        <country>Russian Federation</country>
      </address>
    </facility>
  </location>
  <location>
    <facility>
      <address>
        <city>Kyiv</city>
        <zip>01119</zip>
        <country>Ukraine</country>
      </address>
    </facility>
  </location>
  <location>
    <facility>
      <address>
        <city>Kyiv</city>
        <zip>04050</zip>
        <country>Ukraine</country>
      </address>
    </facility>
  </location>
  <location>
    <facility>
      <address>
        <city>Birmingham</city>
        <zip>B4 6NH</zip>
        <country>United Kingdom</country>
      </address>
    </facility>
  </location>
  <location>
    <facility>
      <address>
        <city>London</city>
        <zip>SE5 9RS</zip>
        <country>United Kingdom</country>
      </address>
    </facility>
  </location>
  <location>
    <facility>
      <address>
        <city>London</city>
        <zip>W2 1PG</zip>
        <country>United Kingdom</country>
      </address>
    </facility>
  </location>
  <location_countries>
    <country>Australia</country>
    <country>Belgium</country>
    <country>Bulgaria</country>
    <country>China</country>
    <country>Germany</country>
    <country>Israel</country>
    <country>Italy</country>
    <country>Poland</country>
    <country>Russian Federation</country>
    <country>Ukraine</country>
    <country>United Kingdom</country>
    <country>United States</country>
  </location_countries>
  <removed_countries>
    <country>Brazil</country>
  </removed_countries>
  <verification_date>December 2015</verification_date>
  <lastchanged_date>December 1, 2015</lastchanged_date>
  <firstreceived_date>December 6, 2011</firstreceived_date>
  <responsible_party>
    <responsible_party_type>Sponsor</responsible_party_type>
  </responsible_party>
  <is_fda_regulated>Yes</is_fda_regulated>
  <is_section_801>Yes</is_section_801>
  <has_expanded_access>No</has_expanded_access>
  <condition_browse>
    <!-- CAUTION:  The following MeSH terms are assigned with an imperfect algorithm  -->
    <mesh_term>Hepatitis</mesh_term>
    <mesh_term>Hepatitis A</mesh_term>
    <mesh_term>Hepatitis B</mesh_term>
    <mesh_term>Hepatitis B, Chronic</mesh_term>
    <mesh_term>Hepatitis, Chronic</mesh_term>
  </condition_browse>
  <intervention_browse>
    <!-- CAUTION:  The following MeSH terms are assigned with an imperfect algorithm  -->
    <mesh_term>Interferon-alpha</mesh_term>
    <mesh_term>Peginterferon alfa-2a</mesh_term>
  </intervention_browse>
  <!-- Results have not yet been posted for this study                                -->
</clinical_study>
