<?xml version="1.0" encoding="UTF-8"?>
<clinical_study rank="194">
  <!-- This xml conforms to an XML Schema at:
    https://clinicaltrials.gov/ct2/html/images/info/public.xsd
 and an XML DTD at:
    https://clinicaltrials.gov/ct2/html/images/info/public.dtd -->
  <required_header>
    <download_date>ClinicalTrials.gov processed this data on December 13, 2015</download_date>
    <link_text>Link to the current ClinicalTrials.gov record.</link_text>
    <url>https://clinicaltrials.gov/show/NCT00940485</url>
  </required_header>
  <id_info>
    <org_study_id>ML22265</org_study_id>
    <nct_id>NCT00940485</nct_id>
  </id_info>
  <brief_title>A Study of Combination or Sequential Treatment With PEGASYS (Peginterferon Alfa-2a) and Entecavir in Patients With HBeAg Positive Chronic Hepatitis B</brief_title>
  <official_title>A Study on Optimizing HBeAg Seroconversion in HBeAg Positive CHB Patients With Combination or Sequential Treatment of Pegylated Interferon Alpha-2a and Entecavir</official_title>
  <sponsors>
    <lead_sponsor>
      <agency>Hoffmann-La Roche</agency>
      <agency_class>Industry</agency_class>
    </lead_sponsor>
  </sponsors>
  <source>Hoffmann-La Roche</source>
  <oversight_info>
    <authority>China: Ministry of Health</authority>
  </oversight_info>
  <brief_summary>
    <textblock>
      This 2 arm study will assess the efficacy and safety of Pegasys in combination or sequential
      treatment with entecavir in patients with HBeAg positive chronic hepatitis B. Patients who
      have been pretreated with, and responded to, entecavir for 9 to 36 months were randomized to
      one of 2 groups, to receive Pegasys 180micrograms/week sc for 48 weeks + entecavir 0.5mg po
      daily for 8 weeks, or entecavir 0.5mg po daily for 48 weeks. The anticipated time on study
      treatment is 3-12 months.
    </textblock>
  </brief_summary>
  <overall_status>Completed</overall_status>
  <start_date>April 2009</start_date>
  <completion_date type="Actual">December 2011</completion_date>
  <primary_completion_date type="Actual">December 2011</primary_completion_date>
  <phase>Phase 4</phase>
  <study_type>Interventional</study_type>
  <study_design>Allocation: Randomized, Endpoint Classification: Safety/Efficacy Study, Intervention Model: Parallel Assignment, Masking: Open Label, Primary Purpose: Treatment</study_design>
  <primary_outcome>
    <measure>HBeAg seroconversion</measure>
    <time_frame>Week 48</time_frame>
    <safety_issue>No</safety_issue>
  </primary_outcome>
  <secondary_outcome>
    <measure>Loss of HBeAg; proportion of patients who achieve HBV DNA &lt;1000 copies/mL;ALT normalization; quantitative HBeAg and HBsAg measurement;HBsAg loss/seroconversion</measure>
    <time_frame>Week 48</time_frame>
    <safety_issue>No</safety_issue>
  </secondary_outcome>
  <secondary_outcome>
    <measure>Adverse events, laboratory parameters, vital signs</measure>
    <time_frame>Week 48</time_frame>
    <safety_issue>No</safety_issue>
  </secondary_outcome>
  <number_of_arms>2</number_of_arms>
  <enrollment type="Actual">200</enrollment>
  <condition>Hepatitis B, Chronic</condition>
  <arm_group>
    <arm_group_label>1</arm_group_label>
    <arm_group_type>Experimental</arm_group_type>
  </arm_group>
  <arm_group>
    <arm_group_label>2</arm_group_label>
    <arm_group_type>Active Comparator</arm_group_type>
  </arm_group>
  <intervention>
    <intervention_type>Drug</intervention_type>
    <intervention_name>entecavir</intervention_name>
    <description>0.5mg po daily for 8 weeks</description>
    <arm_group_label>1</arm_group_label>
  </intervention>
  <intervention>
    <intervention_type>Drug</intervention_type>
    <intervention_name>entecavir</intervention_name>
    <description>0.5mg po daily for 48 weeks</description>
    <arm_group_label>2</arm_group_label>
  </intervention>
  <intervention>
    <intervention_type>Drug</intervention_type>
    <intervention_name>peginterferon alfa-2a [Pegasys]</intervention_name>
    <description>180 micrograms sc/week for 48 weeks</description>
    <arm_group_label>1</arm_group_label>
  </intervention>
  <eligibility>
    <criteria>
      <textblock>
        Inclusion Criteria:

          -  Adult patients, &gt;=18 and &lt;/= 65 years of age

          -  HBeAg positive chronic hepatitis B

          -  Pre-treatment with entecavir for 9-36 months

        Exclusion Criteria:

          -  Antiviral, antineoplastic or immunomodulatory treatment

          -  Co-infection with active hepatitis A, C or D, or HIV

          -  Evidence of decompensated liver disease

          -  History or other evidence of a medical condition associated with chronic liver
             disease other than viral hepatitis
      </textblock>
    </criteria>
    <gender>Both</gender>
    <minimum_age>18 Years</minimum_age>
    <maximum_age>65 Years</maximum_age>
    <healthy_volunteers>No</healthy_volunteers>
  </eligibility>
  <overall_official>
    <last_name>Clinical Trials</last_name>
    <role>Study Director</role>
    <affiliation>Hoffmann-La Roche</affiliation>
  </overall_official>
  <location>
    <facility>
      <address>
        <city>Changsha</city>
        <zip>410008</zip>
        <country>China</country>
      </address>
    </facility>
  </location>
  <location>
    <facility>
      <address>
        <city>Chengdu</city>
        <zip>610041</zip>
        <country>China</country>
      </address>
    </facility>
  </location>
  <location>
    <facility>
      <address>
        <city>Fu Zhou</city>
        <zip>350005</zip>
        <country>China</country>
      </address>
    </facility>
  </location>
  <location>
    <facility>
      <address>
        <city>Guangzhou</city>
        <zip>510515</zip>
        <country>China</country>
      </address>
    </facility>
  </location>
  <location>
    <facility>
      <address>
        <city>Hangzhou</city>
        <zip>310003</zip>
        <country>China</country>
      </address>
    </facility>
  </location>
  <location>
    <facility>
      <address>
        <city>Wuhan</city>
        <zip>430030</zip>
        <country>China</country>
      </address>
    </facility>
  </location>
  <location>
    <facility>
      <address>
        <city>Xi'an</city>
        <zip>710038</zip>
        <country>China</country>
      </address>
    </facility>
  </location>
  <location_countries>
    <country>China</country>
  </location_countries>
  <verification_date>November 2015</verification_date>
  <lastchanged_date>November 2, 2015</lastchanged_date>
  <firstreceived_date>June 16, 2009</firstreceived_date>
  <responsible_party>
    <responsible_party_type>Sponsor</responsible_party_type>
  </responsible_party>
  <is_fda_regulated>No</is_fda_regulated>
  <has_expanded_access>No</has_expanded_access>
  <condition_browse>
    <!-- CAUTION:  The following MeSH terms are assigned with an imperfect algorithm  -->
    <mesh_term>Hepatitis</mesh_term>
    <mesh_term>Hepatitis B</mesh_term>
    <mesh_term>Hepatitis B, Chronic</mesh_term>
  </condition_browse>
  <intervention_browse>
    <!-- CAUTION:  The following MeSH terms are assigned with an imperfect algorithm  -->
    <mesh_term>Entecavir</mesh_term>
    <mesh_term>Interferon-alpha</mesh_term>
    <mesh_term>Peginterferon alfa-2a</mesh_term>
  </intervention_browse>
  <!-- Results have not yet been posted for this study                                -->
</clinical_study>
